LICENSE
keep_exporter/__init__.py
keep_exporter/__main__.py
keep_exporter/cli.py
keep_exporter/export.py
keep_exporter-2.0.1.dist-info/entry_points.txt
keep_exporter-2.0.1.dist-info/LICENSE
keep_exporter-2.0.1.dist-info/WHEEL
keep_exporter-2.0.1.dist-info/METADATA
keep_exporter-2.0.1.dist-info/RECORD
