Metadata-Version: 2.1
Name: keep-exporter
Version: 2.0.1
Summary: Google Keep note exporter utility
Home-page: https://github.com/ndbeals/keep-exporter
License: BSD-3-Clause
Keywords: google,google keep,keep,note,export,archive,backup
Author: Nathan Beals
Author-email: ndbeals@users.noreply.github.com
Requires-Python: >=3.6,<4.0
Classifier: Environment :: Console
Classifier: License :: OSI Approved :: BSD License
Classifier: Operating System :: OS Independent
Classifier: Programming Language :: Python :: 3
Classifier: Programming Language :: Python :: 3.6
Classifier: Programming Language :: Python :: 3.7
Classifier: Programming Language :: Python :: 3.8
Classifier: Programming Language :: Python :: 3.9
Classifier: Topic :: System :: Archiving
Classifier: Topic :: System :: Archiving :: Backup
Classifier: Topic :: Terminals
Classifier: Topic :: Utilities
Requires-Dist: PyYAML (>=5.3.1,<6.0.0)
Requires-Dist: click (>=8.0.1,<9.0.0)
Requires-Dist: click-config-file (>=0.6.0,<0.7.0)
Requires-Dist: gkeepapi (>=0.13.4,<0.14.0)
Requires-Dist: mdutils (>=1.3.0,<2.0.0)
Requires-Dist: pathvalidate (>=2.3.2,<3.0.0)
Requires-Dist: python-frontmatter (>=0.5.0,<0.6.0)
Project-URL: Repository, https://github.com/ndbeals/keep-exporter
